LICENSE
MANIFEST.in
README.md
setup.cfg
setup.py
neom/__init__.py
neom/apps.py
neom/core/ioc.py
neom/ddd/staff.py
neom/ddd/shared/__init__.py
neom/ddd/shared/bypass.py
neom/ddd/shared/entity.py
neom/ddd/shared/entity_support.py
neom/ddd/shared/exceptions.py
neom/ddd/shared/identity.py
neom/ddd/shared/stuff.py
neom/ddd/shared/value_object.py
neom/ddd/shared/value_object_support.py
neom/lib/enum.py
neom/management/commands/autoformat.py
neom/management/commands/coverage.py
neom/management/commands/db-populate.py
neom/management/commands/db-reset.py
neom/management/commands/validate-coverage.py
neom/templatetags/neom.py
neompy.egg-info/PKG-INFO
neompy.egg-info/SOURCES.txt
neompy.egg-info/dependency_links.txt
neompy.egg-info/requires.txt
neompy.egg-info/top_level.txt